{"frames":{"001.png":{"frame":{"x":0,"y":0,"w":8,"h":10,"idx":0},"rotated":false,"trimed":false,"spriteSourceSize":{"x":0,"y":0,"w":8,"h":10},"sourceSize":{"w":8,"h":10}},"002.png":{"frame":{"x":0,"y":12,"w":392,"h":358,"idx":0},"rotated":false,"trimed":false,"spriteSourceSize":{"x":0,"y":0,"w":392,"h":358},"sourceSize":{"w":392,"h":358}},"003.png":{"frame":{"x":394,"y":0,"w":23,"h":31,"idx":0},"rotated":false,"trimed":false,"spriteSourceSize":{"x":0,"y":0,"w":23,"h":31},"sourceSize":{"w":23,"h":31}}},"meta":{"app":"http://www.layabox.com","prefix":"niuniu_psd/VIP/","version":"1.0","image":"VIP.png","format":"","size":{"w":512,"h":512},"scale":"1"}}